drf_friend/__init__.py
drf_friend/celery.py
drf_friend/core.py
drf_friend/drf_dto.py
drf_friend/env.py
drf_friend/managers.py
drf_friend/models.py
drf_friend/paginate.py
drf_friend/path.py
drf_friend/router.py
drf_friend/status.py
drf_friend/config/__init__.py
drf_friend/config/database.py
drf_friend/cors/__init__.py
drf_friend/cors/apps.py
drf_friend/cors/checks.py
drf_friend/cors/conf.py
drf_friend/cors/defaults.py
drf_friend/cors/middleware.py
drf_friend/cors/signals.py
drf_friend/drf_core/__init__.py
drf_friend/drf_core/index.py
drf_friend/drf_core/serializers.py
drf_friend/filesystem/__init__.py
drf_friend/filesystem/storage.py
drf_friend/filesystem/the_disks/__init__.py
drf_friend/filesystem/the_disks/local.py
drf_friend/filesystem/the_disks/s3.py
drf_friend/initialize/__init__.py
drf_friend/initialize/initialize.py
drf_friend/mailer/__init__.py
drf_friend/mailer/inline_css.py
drf_friend/mailer/send_mail.py
drf_friend/mailer/send_mail_queue.py
drf_friend/project/__init__.py
drf_friend/project/apps.py
drf_friend/project/models.py
drf_friend/project/tasks.py
drf_friend/project/urls.py
drf_friend/project/views.py
drf_friend/project/middleware/APILoggerMiddleware.py
drf_friend/project/middleware/__init__.py
drf_friend/project/migrations/__init__.py
drf_friend/project/utils/__init__.py
drf_friend/project/utils/system_environment.py
drf_friend/raw_query/__init__.py
drf_friend/raw_query/helpers.py
drf_friend/raw_query/serializer.py
drf_friend/scheduler/__init__.py
drf_friend/scheduler/schedule.py
drf_friend/scheduler/schedule_cron.py
drf_friend-0.0.30.dist-info/LICENSE
drf_friend-0.0.30.dist-info/METADATA
drf_friend-0.0.30.dist-info/WHEEL
drf_friend-0.0.30.dist-info/top_level.txt
drf_friend-0.0.30.dist-info/RECORD
