Metadata-Version: 2.1
Name: drf-friend
Version: 0.0.30
Summary: A utility package for Django Rest Framework (DRF) that makes API development easier for developers.
Home-page: https://drf-friend.code4mk.org/
Author: Mostafa Kamal
Author-email: hiremostafa@gmail.com
Project-URL: Source, https://github.com/code4mk/drf-friend
Project-URL: Changelog, https://github.com/code4mk/drf-friend
Keywords: django,drf,django-rest-framework,django-rest-api,drf_friend,code4mk
Classifier: Development Status :: 3 - Alpha
Classifier: Intended Audience :: Developers
Classifier: License :: OSI Approved :: MIT License
Classifier: Programming Language :: Python :: 3
Classifier: Programming Language :: Python :: 3.6
Classifier: Programming Language :: Python :: 3.7
Classifier: Programming Language :: Python :: 3.8
Classifier: Programming Language :: Python :: 3.9
License-File: LICENSE
Requires-Dist: redis
Requires-Dist: boto3
Requires-Dist: psycopg2-binary
Requires-Dist: django-rest-framework
Requires-Dist: python-dotenv
Requires-Dist: celery
Requires-Dist: beautifulsoup4
Requires-Dist: premailer
Requires-Dist: celery-redbeat
